LNMarkets/APIUrls.py
LNMarkets/History.py
LNMarkets/Positions.py
LNMarkets/State.py
LNMarkets/User.py
LNMarkets/__init__.py
LNMarkets-1.4.0.dist-info/LICENSE
LNMarkets-1.4.0.dist-info/METADATA
LNMarkets-1.4.0.dist-info/WHEEL
LNMarkets-1.4.0.dist-info/top_level.txt
LNMarkets-1.4.0.dist-info/RECORD
