Metadata-Version: 2.1
Name: LNMarkets
Version: 1.4.0
Summary: LNMarkets API Wrapper
Home-page: https://github.com/DivyanshuBagga/LNMarkets
Author: Divyanshu Bagga
Author-email: divyanshu.baggar@pm.me
License: MIT
Download-URL: https://github.com/DivyanshuBagga/LNMarkets/archive/1.3.0.tar.gz
Keywords: Bitcoin,Finance,Trading
Platform: UNKNOWN
Requires-Python: >=3.6
Requires-Dist: requests
